django_su/__init__.py
django_su/apps.py
django_su/conf.py
django_su/management/__init__.py
django_su/management/commands/__init__.py
django_su/management/commands/create_dev_su.py
django_su/management/commands/util_restore.py
django_su/migrations/__init__.py
django_dev_superuser-0.2.0.dist-info/METADATA
django_dev_superuser-0.2.0.dist-info/WHEEL
django_dev_superuser-0.2.0.dist-info/top_level.txt
django_dev_superuser-0.2.0.dist-info/RECORD
