Metadata-Version: 2.1
Name: django-dev-superuser
Version: 0.2.0
Summary: Management commands to creating super user with ease.
Author-email: Jerin Peter George <jerinpetergeorge@gmail.com>
Project-URL: Homepage, https://github.com/jerinpetergeorge/django-dev-superuser
Classifier: Environment :: Web Environment
Classifier: Environment :: Console
Classifier: Framework :: Django :: 2.2
Classifier: Framework :: Django :: 3.2
Classifier: Framework :: Django :: 4.0
Classifier: Intended Audience :: Developers
Classifier: Operating System :: OS Independent
Classifier: Programming Language :: Python
Classifier: Programming Language :: Python :: 3.7
Classifier: Programming Language :: Python :: 3.8
Classifier: Programming Language :: Python :: 3.9
Classifier: Programming Language :: Python :: 3.10
Classifier: Topic :: Utilities
Requires-Dist: Django >=2.2
Requires-Dist: django-extensions
Provides-Extra: dev
Requires-Dist: bump2version ~=1.0.1 ; extra == 'dev'
